sjfirebaseai/__init__.py
sjfirebaseai/jclass/__init__.py
sjfirebaseai/jclass/blokthreshold.py
sjfirebaseai/jclass/config.py
sjfirebaseai/jclass/content.py
sjfirebaseai/jclass/firebaseai.py
sjfirebaseai/jclass/functiondeclaration.py
sjfirebaseai/jclass/functionresponsepart.py
sjfirebaseai/jclass/fvai.py
sjfirebaseai/jclass/gb.py
sjfirebaseai/jclass/gcbuilder.py
sjfirebaseai/jclass/gcr.py
sjfirebaseai/jclass/gmf.py
sjfirebaseai/jclass/googlesearch.py
sjfirebaseai/jclass/harmcategory.py
sjfirebaseai/jclass/optionals.py
sjfirebaseai/jclass/safetysettings.py
sjfirebaseai/jclass/schema.py
sjfirebaseai/jclass/tool.py
sjfirebaseai/jinterface/__init__.py
sjfirebaseai-1.1.0.dist-info/LICENSE
sjfirebaseai-1.1.0.dist-info/METADATA
sjfirebaseai-1.1.0.dist-info/WHEEL
sjfirebaseai-1.1.0.dist-info/RECORD
