Metadata-Version: 2.1
Name: sjfirebaseai
Version: 1.1.0
Summary: 
Author: Kenechukwu Akubue
Author-email: kengoon19@gmail.com
Requires-Python: >=3.13,<4.0
Classifier: Programming Language :: Python :: 3
Requires-Dist: pyjnius (>=1.6.1,<2.0.0)
